habluetooth/__init__.py
habluetooth/advertisement_tracker.cpython-314-x86_64-linux-musl.so
habluetooth/advertisement_tracker.pxd
habluetooth/advertisement_tracker.py
habluetooth/base_scanner.cpython-314-x86_64-linux-musl.so
habluetooth/base_scanner.pxd
habluetooth/base_scanner.py
habluetooth/central_manager.py
habluetooth/const.py
habluetooth/manager.cpython-314-x86_64-linux-musl.so
habluetooth/manager.pxd
habluetooth/manager.py
habluetooth/models.cpython-314-x86_64-linux-musl.so
habluetooth/models.pxd
habluetooth/models.py
habluetooth/py.typed
habluetooth/scanner.cpython-314-x86_64-linux-musl.so
habluetooth/scanner.pxd
habluetooth/scanner.py
habluetooth/scanner_device.py
habluetooth/storage.py
habluetooth/usage.py
habluetooth/util.py
habluetooth/wrappers.py
habluetooth/channels/bluez.cpython-314-x86_64-linux-musl.so
habluetooth/channels/bluez.pxd
habluetooth/channels/bluez.py
habluetooth-5.6.4.dist-info/LICENSE
habluetooth-5.6.4.dist-info/METADATA
habluetooth-5.6.4.dist-info/WHEEL
habluetooth-5.6.4.dist-info/RECORD
