Metadata-Version: 2.3
Name: habluetooth
Version: 5.6.4
Summary: High availability Bluetooth
License: Apache-2.0
Author: J. Nick Koston
Author-email: bluetooth@koston.org
Requires-Python: >=3.11
Classifier: Development Status :: 2 - Pre-Alpha
Classifier: Intended Audience :: Developers
Classifier: License :: OSI Approved :: Apache Software License
Classifier: Natural Language :: English
Classifier: Operating System :: OS Independent
Classifier: Programming Language :: Python :: 3
Classifier: Programming Language :: Python :: 3.11
Classifier: Programming Language :: Python :: 3.12
Classifier: Programming Language :: Python :: 3.13
Classifier: Topic :: Software Development :: Libraries
Requires-Dist: async-interrupt (>=1.1.1)
Requires-Dist: bleak (>=1.0.1)
Requires-Dist: bleak-retry-connector (>=4.2.0)
Requires-Dist: bluetooth-adapters (>=2.1.0)
Requires-Dist: bluetooth-auto-recovery (>=1.5.1)
Requires-Dist: bluetooth-data-tools (>=1.28.0)
Requires-Dist: btsocket (>=0.3.0)
Requires-Dist: dbus-fast (>=2.30.2) ; platform_system == "Linux"
Project-URL: Bug Tracker, https://github.com/bluetooth-devices/habluetooth/issues
Project-URL: Changelog, https://github.com/bluetooth-devices/habluetooth/blob/main/CHANGELOG.md
Project-URL: Documentation, https://habluetooth.readthedocs.io
Project-URL: Repository, https://github.com/bluetooth-devices/habluetooth
